rtl/low_power_alu.v
//====================================================
// Low Power ALU Design using Verilog
// 8-bit Parameterized ALU
// Operand Isolation based Low Power Concept
//====================================================

module low_power_alu #(
    parameter WIDTH = 8
)
(
    input  [WIDTH-1:0] A,
    input  [WIDTH-1:0] B,
    input  [3:0] opcode,
    input enable,

    output reg [WIDTH-1:0] result,

    output reg zero_flag,
    output reg carry_flag,
    output reg overflow_flag,
    output reg negative_flag
);


// Temporary variable
reg [WIDTH:0] temp;


// ALU Operation

always @(*)
begin

    // Default values
    result = 0;
    carry_flag = 0;
    overflow_flag = 0;


    // Low Power Operand Isolation
    // When enable = 0, computation stops

    if(enable)
    begin

        case(opcode)

        4'b0000:        // ADD
        begin
            temp = A + B;
            result = temp[WIDTH-1:0];
            carry_flag = temp[WIDTH];
        end


        4'b0001:        // SUB
        begin
            result = A - B;
        end


        4'b0010:        // AND
        begin
            result = A & B;
        end


        4'b0011:        // OR
        begin
            result = A | B;
        end


        4'b0100:        // XOR
        begin
            result = A ^ B;
        end


        4'b0101:        // NOT A
        begin
            result = ~A;
        end


        4'b0110:        // Shift Left
        begin
            result = A << 1;
        end


        4'b0111:        // Shift Right
        begin
            result = A >> 1;
        end


        4'b1000:        // Increment
        begin
            result = A + 1;
        end


        4'b1001:        // Decrement
        begin
            result = A - 1;
        end


        4'b1010:        // Compare
        begin

            if(A>B)
                result = 8'b00000001;

            else if(A<B)
                result = 8'b00000010;

            else
                result = 8'b00000000;

        end


        default:
        begin
            result = 0;
        end


        endcase

    end

    else
    begin
        result = 0;
    end



    // Flag Generation

    zero_flag = (result == 0);

    negative_flag = result[WIDTH-1];



    // Overflow detection

    if(opcode == 4'b0000)
        overflow_flag = 
        (~(A[7]^B[7])) & (result[7]^A[7]);

    else if(opcode == 4'b0001)
        overflow_flag =
        ((A[7]^B[7])) & (result[7]^A[7]);

    else
        overflow_flag = 0;


end

endmodule

tb/low_power_alu_tb.v
//====================================================
// Low Power ALU Testbench
//====================================================

`timescale 1ns/1ps

module low_power_alu_tb;

parameter WIDTH = 8;


// Inputs
reg [WIDTH-1:0] A;
reg [WIDTH-1:0] B;
reg [3:0] opcode;
reg enable;


// Outputs
wire [WIDTH-1:0] result;
wire zero_flag;
wire carry_flag;
wire overflow_flag;
wire negative_flag;


// Waveform generation

initial
begin
    $dumpfile("dump.vcd");
    $dumpvars(0, low_power_alu_tb);
end



// ALU Instance

low_power_alu #(WIDTH) DUT
(
    .A(A),
    .B(B),
    .opcode(opcode),
    .enable(enable),

    .result(result),

    .zero_flag(zero_flag),
    .carry_flag(carry_flag),
    .overflow_flag(overflow_flag),
    .negative_flag(negative_flag)
);



initial
begin

$display("--------------------------------");
$display("LOW POWER ALU VERIFICATION");
$display("--------------------------------");


$monitor(
"Time=%0t | A=%d B=%d | Opcode=%b | Result=%d | Z=%b C=%b O=%b N=%b",
$time,
A,
B,
opcode,
result,
zero_flag,
carry_flag,
overflow_flag,
negative_flag
);


// Enable ALU

enable = 1;



// ADD Test

A = 8'd10;
B = 8'd5;
opcode = 4'b0000;

#10;


// SUB Test

A = 8'd20;
B = 8'd8;
opcode = 4'b0001;

#10;


// AND Test

A = 8'b11110000;
B = 8'b00001111;
opcode = 4'b0010;

#10;


// OR Test

opcode = 4'b0011;

#10;


// XOR Test

opcode = 4'b0100;

#10;


// NOT A Test

A = 8'b10101010;
opcode = 4'b0101;

#10;


// SHIFT LEFT

A = 8'b00001111;
opcode = 4'b0110;

#10;


// SHIFT RIGHT

A = 8'b11110000;
opcode = 4'b0111;

#10;


// Increment

A = 8'd25;
opcode = 4'b1000;

#10;


// Decrement

A = 8'd25;
opcode = 4'b1001;

#10;


// Compare A>B

A = 8'd30;
B = 8'd10;
opcode = 4'b1010;

#10;


// Compare A<B

A = 8'd5;
B = 8'd20;
opcode = 4'b1010;

#10;


// Compare Equal

A = 8'd15;
B = 8'd15;
opcode = 4'b1010;

#10;


// Disable ALU (Low Power Mode)

enable = 0;

A = 8'd100;
B = 8'd50;
opcode = 4'b0000;

#10;



$display("--------------------------------");
$display("SIMULATION COMPLETED SUCCESSFULLY");
$display("--------------------------------");


$finish;


end


endmodule

tb/dump.vcd
$date
	Thu Jun 18 02:59:56 2026
$end
$version
	Icarus Verilog
$end
$timescale
	1ps
$end
$scope module low_power_alu_tb $end
$var wire 1 ! zero_flag $end
$var wire 8 " result [7:0] $end
$var wire 1 # overflow_flag $end
$var wire 1 $ negative_flag $end
$var wire 1 % carry_flag $end
$var parameter 32 & WIDTH $end
$var reg 8 ' A [7:0] $end
$var reg 8 ( B [7:0] $end
$var reg 1 ) enable $end
$var reg 4 * opcode [3:0] $end
$scope module DUT $end
$var wire 8 + A [7:0] $end
$var wire 8 , B [7:0] $end
$var wire 1 ) enable $end
$var wire 4 - opcode [3:0] $end
$var parameter 32 . WIDTH $end
$var reg 1 % carry_flag $end
$var reg 1 $ negative_flag $end
$var reg 1 # overflow_flag $end
$var reg 8 / result [7:0] $end
$var reg 9 0 temp [8:0] $end
$var reg 1 ! zero_flag $end
$upscope $end
$upscope $end
$enddefinitions $end
$comment Show the parameter values. $end
$dumpall
b1000 .
b1000 &
$end
#0
$dumpvars
b1111 0
b1111 /
b0 -
b101 ,
b1010 +
b0 *
1)
b101 (
b1010 '
0%
0$
0#
b1111 "
0!
$end
#10000
b1100 "
b1100 /
b1 *
b1 -
b1000 (
b1000 ,
b10100 '
b10100 +
#20000
1!
b0 "
b0 /
b10 *
b10 -
b1111 (
b1111 ,
b11110000 '
b11110000 +
#30000
1$
0!
b11111111 "
b11111111 /
b11 *
b11 -
#40000
b11111111 "
b11111111 /
b100 *
b100 -
#50000
0$
b1010101 "
b1010101 /
b101 *
b101 -
b10101010 '
b10101010 +
#60000
b11110 "
b11110 /
b110 *
b110 -
b1111 '
b1111 +
#70000
b1111000 "
b1111000 /
b111 *
b111 -
b11110000 '
b11110000 +
#80000
b11010 "
b11010 /
b1000 *
b1000 -
b11001 '
b11001 +
#90000
b11000 "
b11000 /
b1001 *
b1001 -
#100000
b1 "
b1 /
b1010 *
b1010 -
b1010 (
b1010 ,
b11110 '
b11110 +
#110000
b10 "
b10 /
b10100 (
b10100 ,
b101 '
b101 +
#120000
1!
b0 "
b0 /
b1111 (
b1111 ,
b1111 '
b1111 +
#130000
b0 *
b0 -
b110010 (
b110010 ,
b1100100 '
b1100100 +
0)
